small_py-0.2.3.dist-info/licenses/LICENSE
smallpy/__init__.py
smallpy/utils.py
small_py-0.2.3.dist-info/METADATA
small_py-0.2.3.dist-info/WHEEL
small_py-0.2.3.dist-info/top_level.txt
small_py-0.2.3.dist-info/RECORD
