Metadata-Version: 2.4
Name: small-py
Version: 0.2.3
Summary: Utility library for various uses
Author-email: Nathan Smalley <nathansmalley2@gmail.com>
License: MIT
Requires-Python: >=3.12
License-File: LICENSE
Requires-Dist: pandas
Requires-Dist: pyautogui
Dynamic: license-file
